[[{"s":148,"f":24},{"s":148,"f":25},{"s":148,"f":26},{"s":148,"f":27},{"s":148,"f":28},{"s":148,"f":29},{"s":148,"f":30},{"s":148,"f":31},{"s":147,"f":0},{"s":147,"f":1},{"s":147,"f":2},{"s":147,"f":3},{"s":147,"f":4},{"s":147,"f":5},{"s":147,"f":6},{"s":147,"f":7}],[{"s":147,"f":0},{"s":147,"f":1},{"s":147,"f":2},{"s":147,"f":3},{"s":147,"f":4},{"s":147,"f":5},{"s":147,"f":6},{"s":147,"f":7},{"s":147,"f":8},{"s":147,"f":9},{"s":147,"f":10},{"s":147,"f":11},{"s":147,"f":12},{"s":147,"f":13},{"s":147,"f":14},{"s":147,"f":15}],[{"s":147,"f":8},{"s":147,"f":9},{"s":147,"f":10},{"s":147,"f":11},{"s":147,"f":12},{"s":147,"f":13},{"s":147,"f":14},{"s":147,"f":15},{"s":147,"f":16},{"s":147,"f":17},{"s":147,"f":18},{"s":147,"f":19},{"s":147,"f":20},{"s":147,"f":21},{"s":147,"f":22},{"s":147,"f":23}],[{"s":147,"f":16},{"s":147,"f":17},{"s":147,"f":18},{"s":147,"f":19},{"s":147,"f":20},{"s":147,"f":21},{"s":147,"f":22},{"s":147,"f":23},{"s":147,"f":24},{"s":147,"f":25},{"s":147,"f":26},{"s":147,"f":27},{"s":147,"f":28},{"s":147,"f":29},{"s":147,"f":30},{"s":147,"f":31}],[{"s":147,"f":24},{"s":147,"f":25},{"s":147,"f":26},{"s":147,"f":27},{"s":147,"f":28},{"s":147,"f":29},{"s":147,"f":30},{"s":147,"f":31},{"s":309,"f":1},{"s":148,"f":1},{"s":148,"f":2},{"s":148,"f":3},{"s":138,"f":4},{"s":138,"f":5},{"s":138,"f":6},{"s":138,"f":7}],[{"s":138,"f":12},{"s":138,"f":13},{"s":138,"f":14},{"s":138,"f":15},{"s":134,"f":12},{"s":134,"f":13},{"s":148,"f":14},{"s":148,"f":15},{"s":148,"f":8},{"s":148,"f":9},{"s":137,"f":1},{"s":137,"f":2},{"s":137,"f":3},{"s":138,"f":13},{"s":138,"f":14},{"s":138,"f":15}],[{"s":138,"f":20},{"s":138,"f":21},{"s":138,"f":22},{"s":138,"f":23},{"s":134,"f":29},{"s":134,"f":21},{"s":148,"f":22},{"s":148,"f":23},{"s":148,"f":16},{"s":148,"f":17},{"s":137,"f":9},{"s":137,"f":10},{"s":137,"f":11},{"s":138,"f":21},{"s":138,"f":22},{"s":138,"f":23}],[{"s":138,"f":28},{"s":138,"f":29},{"s":138,"f":30},{"s":138,"f":31},{"s":23,"f":0},{"s":143,"f":6},{"s":143,"f":7},{"s":148,"f":31},{"s":148,"f":24},{"s":148,"f":25},{"s":137,"f":17},{"s":137,"f":18},{"s":137,"f":19},{"s":138,"f":29},{"s":138,"f":30},{"s":22,"f":3}],[{"s":22,"f":0},{"s":23,"f":0},{"s":23,"f":0},{"s":22,"f":3},{"s":23,"f":0},{"s":143,"f":14},{"s":143,"f":15},{"s":148,"f":5},{"s":148,"f":6},{"s":148,"f":7},{"s":137,"f":25},{"s":137,"f":26},{"s":137,"f":27},{"s":23,"f":0},{"s":22,"f":5},{"s":117,"f":23}],[{"s":8,"f":9},{"s":22,"f":1},{"s":22,"f":5},{"s":117,"f":23},{"s":22,"f":0},{"s":23,"f":0},{"s":143,"f":18},{"s":143,"f":2},{"s":143,"f":3},{"s":142,"f":4},{"s":142,"f":5},{"s":142,"f":6},{"s":23,"f":0},{"s":23,"f":0},{"s":22,"f":7},{"s":113,"f":8}],[{"s":8,"f":9},{"s":117,"f":23},{"s":117,"f":30},{"s":22,"f":25},{"s":22,"f":12},{"s":22,"f":3},{"s":23,"f":0},{"s":143,"f":10},{"s":143,"f":11},{"s":142,"f":12},{"s":142,"f":13},{"s":23,"f":0},{"s":23,"f":0},{"s":22,"f":6},{"s":22,"f":10},{"s":113,"f":7}],[{"s":8,"f":9},{"s":8,"f":9},{"s":8,"f":9},{"s":8,"f":9},{"s":117,"f":31},{"s":117,"f":29},{"s":23,"f":0},{"s":143,"f":18},{"s":143,"f":19},{"s":142,"f":20},{"s":23,"f":0},{"s":145,"f":9},{"s":23,"f":0},{"s":23,"f":0},{"s":23,"f":0},{"s":22,"f":22}],[{"s":8,"f":9},{"s":117,"f":21},{"s":8,"f":9},{"s":8,"f":9},{"s":116,"f":6},{"s":116,"f":7},{"s":22,"f":29},{"s":23,"f":0},{"s":23,"f":0},{"s":23,"f":0},{"s":144,"f":30},{"s":145,"f":16},{"s":23,"f":0},{"s":23,"f":0},{"s":22,"f":5},{"s":117,"f":23}],[{"s":117,"f":4},{"s":117,"f":5},{"s":8,"f":9},{"s":321,"f":0},{"s":116,"f":14},{"s":116,"f":15},{"s":22,"f":0},{"s":23,"f":0},{"s":22,"f":3},{"s":143,"f":5},{"s":143,"f":2},{"s":142,"f":5},{"s":142,"f":6},{"s":22,"f":6},{"s":22,"f":26},{"s":8,"f":9}],[{"s":117,"f":4},{"s":8,"f":9},{"s":8,"f":9},{"s":8,"f":9},{"s":321,"f":3},{"s":117,"f":19},{"s":117,"f":31},{"s":22,"f":2},{"s":22,"f":27},{"s":22,"f":0},{"s":23,"f":0},{"s":22,"f":3},{"s":22,"f":19},{"s":22,"f":4},{"s":8,"f":9},{"s":8,"f":9}],[{"s":117,"f":12},{"s":8,"f":9},{"s":8,"f":9},{"s":8,"f":9},{"s":117,"f":26},{"s":117,"f":27},{"s":8,"f":9},{"s":117,"f":23},{"s":8,"f":9},{"s":117,"f":30},{"s":22,"f":2},{"s":117,"f":22},{"s":22,"f":24},{"s":22,"f":26},{"s":8,"f":9},{"s":335,"f":0}]]