[[{"s":148,"f":4},{"s":148,"f":5},{"s":148,"f":6},{"s":148,"f":7},{"s":148,"f":6},{"s":24,"f":3},{"s":24,"f":0},{"s":24,"f":1},{"s":24,"f":0},{"s":24,"f":1},{"s":24,"f":2},{"s":147,"f":15},{"s":148,"f":12},{"s":148,"f":13},{"s":148,"f":14},{"s":148,"f":15}],[{"s":148,"f":12},{"s":148,"f":13},{"s":148,"f":14},{"s":148,"f":15},{"s":148,"f":14},{"s":24,"f":2},{"s":24,"f":1},{"s":24,"f":1},{"s":24,"f":1},{"s":24,"f":0},{"s":24,"f":3},{"s":147,"f":23},{"s":148,"f":20},{"s":148,"f":21},{"s":148,"f":22},{"s":148,"f":23}],[{"s":148,"f":20},{"s":148,"f":21},{"s":148,"f":22},{"s":148,"f":23},{"s":24,"f":9},{"s":24,"f":20},{"s":24,"f":17},{"s":24,"f":0},{"s":24,"f":0},{"s":24,"f":1},{"s":24,"f":2},{"s":147,"f":31},{"s":148,"f":28},{"s":148,"f":29},{"s":148,"f":30},{"s":148,"f":31}],[{"s":148,"f":28},{"s":148,"f":29},{"s":148,"f":30},{"s":24,"f":9},{"s":24,"f":20},{"s":24,"f":1},{"s":24,"f":1},{"s":24,"f":1},{"s":24,"f":1},{"s":24,"f":1},{"s":24,"f":2},{"s":138,"f":3},{"s":142,"f":4},{"s":142,"f":5},{"s":143,"f":2},{"s":143,"f":3}],[{"s":148,"f":4},{"s":148,"f":5},{"s":24,"f":9},{"s":24,"f":20},{"s":24,"f":1},{"s":24,"f":0},{"s":24,"f":1},{"s":24,"f":0},{"s":24,"f":16},{"s":24,"f":1},{"s":24,"f":3},{"s":138,"f":11},{"s":142,"f":12},{"s":142,"f":13},{"s":143,"f":10},{"s":143,"f":11}],[{"s":24,"f":3},{"s":24,"f":2},{"s":24,"f":20},{"s":24,"f":0},{"s":24,"f":1},{"s":24,"f":1},{"s":24,"f":0},{"s":24,"f":1},{"s":24,"f":1},{"s":24,"f":0},{"s":24,"f":2},{"s":138,"f":19},{"s":142,"f":6},{"s":23,"f":0},{"s":143,"f":18},{"s":143,"f":19}],[{"s":24,"f":1},{"s":24,"f":16},{"s":24,"f":0},{"s":24,"f":1},{"s":24,"f":1},{"s":24,"f":0},{"s":24,"f":1},{"s":24,"f":0},{"s":24,"f":1},{"s":24,"f":0},{"s":24,"f":3},{"s":25,"f":5},{"s":25,"f":4},{"s":25,"f":21},{"s":25,"f":20},{"s":25,"f":5}],[{"s":24,"f":0},{"s":24,"f":1},{"s":24,"f":1},{"s":24,"f":0},{"s":24,"f":1},{"s":24,"f":0},{"s":24,"f":1},{"s":24,"f":1},{"s":24,"f":1},{"s":24,"f":0},{"s":24,"f":2},{"s":23,"f":9},{"s":23,"f":0},{"s":23,"f":4},{"s":23,"f":3},{"s":23,"f":0}],[{"s":24,"f":1},{"s":24,"f":0},{"s":24,"f":0},{"s":24,"f":1},{"s":24,"f":0},{"s":24,"f":1},{"s":24,"f":1},{"s":24,"f":0},{"s":24,"f":0},{"s":24,"f":1},{"s":24,"f":3},{"s":23,"f":4},{"s":23,"f":5},{"s":23,"f":0},{"s":23,"f":4},{"s":23,"f":0}],[{"s":24,"f":0},{"s":24,"f":1},{"s":24,"f":1},{"s":24,"f":0},{"s":24,"f":17},{"s":24,"f":1},{"s":24,"f":0},{"s":24,"f":1},{"s":24,"f":1},{"s":24,"f":1},{"s":24,"f":2},{"s":25,"f":5},{"s":25,"f":4},{"s":25,"f":21},{"s":25,"f":20},{"s":25,"f":5}],[{"s":24,"f":2},{"s":24,"f":3},{"s":24,"f":21},{"s":24,"f":1},{"s":24,"f":1},{"s":24,"f":0},{"s":24,"f":1},{"s":24,"f":0},{"s":24,"f":1},{"s":24,"f":0},{"s":24,"f":3},{"s":139,"f":0},{"s":139,"f":1},{"s":139,"f":2},{"s":144,"f":6},{"s":145,"f":5}],[{"s":147,"f":25},{"s":147,"f":26},{"s":24,"f":8},{"s":24,"f":21},{"s":24,"f":0},{"s":24,"f":0},{"s":24,"f":1},{"s":24,"f":0},{"s":24,"f":1},{"s":24,"f":0},{"s":24,"f":2},{"s":139,"f":8},{"s":139,"f":9},{"s":139,"f":10},{"s":145,"f":13},{"s":144,"f":15}],[{"s":148,"f":0},{"s":148,"f":1},{"s":148,"f":2},{"s":24,"f":8},{"s":24,"f":21},{"s":24,"f":1},{"s":24,"f":0},{"s":24,"f":1},{"s":24,"f":16},{"s":24,"f":1},{"s":24,"f":3},{"s":139,"f":16},{"s":139,"f":17},{"s":145,"f":20},{"s":145,"f":21},{"s":144,"f":23}],[{"s":148,"f":8},{"s":148,"f":9},{"s":148,"f":10},{"s":148,"f":11},{"s":24,"f":8},{"s":24,"f":21},{"s":24,"f":1},{"s":24,"f":1},{"s":24,"f":0},{"s":24,"f":1},{"s":24,"f":2},{"s":139,"f":24},{"s":148,"f":11},{"s":145,"f":28},{"s":144,"f":30},{"s":144,"f":31}],[{"s":148,"f":16},{"s":148,"f":17},{"s":148,"f":18},{"s":148,"f":19},{"s":147,"f":9},{"s":24,"f":3},{"s":24,"f":0},{"s":24,"f":1},{"s":24,"f":1},{"s":24,"f":1},{"s":24,"f":3},{"s":148,"f":3},{"s":148,"f":4},{"s":148,"f":5},{"s":148,"f":6},{"s":148,"f":7}],[{"s":148,"f":24},{"s":148,"f":25},{"s":148,"f":26},{"s":148,"f":27},{"s":147,"f":17},{"s":24,"f":2},{"s":24,"f":0},{"s":24,"f":1},{"s":24,"f":1},{"s":24,"f":17},{"s":24,"f":2},{"s":148,"f":11},{"s":148,"f":12},{"s":148,"f":11},{"s":148,"f":14},{"s":148,"f":15}]]